<?xml version="1.0" encoding="UTF-8"?>
<con:testCase id="4e00dd26-952c-4cce-be52-a31c046ab55a" discardOkResults="true" failOnError="true" failTestCaseOnErrors="true" keepSession="false" name="getallinvitedmember" searchProperties="true" timeout="0" xmlns:con="http://eviware.com/soapui/config">
  <con:settings>
    <con:setting id="7a3c1526-5c87-48c5-956f-a7f284e31d31fileName">getallinvitedmember</con:setting>
    <con:setting id="2e3423e0-791f-4d18-9c0c-f12c849d9145fileName">getallinvitedmember</con:setting>
  <con:setting id="4e00dd26-952c-4cce-be52-a31c046ab55afileName">getallinvitedmember</con:setting></con:settings>
  <con:savedRecentRuns>1</con:savedRecentRuns>
  
  
  
  
  <con:testStep type="restrequest" name="getallinvitedmember" id="c52e4928-c523-478a-9520-0f7db7b101df">
    <con:settings/>
    <con:config service="Create Account" resourcePath="/client_auth/accounts" methodName="Create Account" xsi:type="con:RestRequestStep" xmlns:xsi="http://www.w3.org/2001/XMLSchema-instance">
      <con:restRequest name="getallinvitedmember" id="aa987182-fe19-47f6-8be5-e8a0e93ce082" mediaType="application/json" postQueryString="false">
        <con:settings>
          <con:setting id="com.eviware.soapui.impl.wsdl.WsdlRequest@request-headers">&lt;xml-fragment/></con:setting>
        </con:settings>
        <con:endpoint>${API-Connect}</con:endpoint>
        <con:request/>
        <con:originalUri>https://api-stg.whrcloud.com/api/v1/members/5522</con:originalUri>
        <con:assertion type="Valid HTTP Status Codes" id="9769664d-7f1d-4c5e-b3b6-8ea3d1a1342e" name="Valid HTTP Status Codes"><con:settings/><con:configuration><codes>200</codes></con:configuration></con:assertion><con:credentials>
          <con:selectedAuthProfile>No Authorization</con:selectedAuthProfile>
          <con:authType>No Authorization</con:authType>
        </con:credentials>
        <con:jmsConfig JMSDeliveryMode="PERSISTENT"/>
        <con:parameters><entry key="Authorization" value="bearer ${access_token}" xmlns="http://eviware.com/soapui/config"/></con:parameters>
        <con:parameterOrder>
          <con:entry>Authorization</con:entry>
          <con:entry>wp-client-region</con:entry>
          <con:entry>wp-client-country</con:entry>
          <con:entry>wp-client-brand</con:entry>
        </con:parameterOrder>
      </con:restRequest>
    </con:config>
  </con:testStep>
  
  <con:properties/>
  <con:reportParameters/>
  <con:breakPoints>
    <con:testStepId>3baf989e-8b38-4c2a-9112-95ddf253d4a5</con:testStepId>
    <con:status>NONE</con:status>
    <con:properties/>
  </con:breakPoints>
  <con:breakPoints>
    <con:testStepId>4a8e6344-dea6-4afc-ba5f-3d6fbbf13b9f</con:testStepId>
    <con:status>NONE</con:status>
    <con:properties/>
  </con:breakPoints>
</con:testCase>